{
    "especialidad": "CARDIOLOGÍA PEDIÁTRICA",
    "patologias":[
        {
            "patologia": "",
            "criterios": "",
            "examenes": "",
            "observaciones": ""
        },
        {
            "patologia": "",
            "criterios": "",
            "examenes": "",
            "observaciones": ""
        },
        {
            "patologia": "",
            "criterios": "",
            "examenes": "",
            "observaciones": ""
        },
        {
            "patologia": "",
            "criterios": "",
            "examenes": "",
            "observaciones": ""
        },
        {
            "patologia": "",
            "criterios": "",
            "examenes": "",
            "observaciones": ""
        }
    ]
}